core_scripts_cli/__init__.py
core_scripts_cli/__main__.py
core_scripts_cli-0.1.0.dist-info/METADATA
core_scripts_cli-0.1.0.dist-info/WHEEL
core_scripts_cli-0.1.0.dist-info/RECORD
